odoo/addons/animal_medicament/README.rst
odoo/addons/animal_medicament/__init__.py
odoo/addons/animal_medicament/__manifest__.py
odoo/addons/animal_medicament/i18n/animal_medicament.pot
odoo/addons/animal_medicament/i18n/it.po
odoo/addons/animal_medicament/models/__init__.py
odoo/addons/animal_medicament/models/posology.py
odoo/addons/animal_medicament/models/posology_mixin.py
odoo/addons/animal_medicament/models/product.py
odoo/addons/animal_medicament/readme/DESCRIPTION.rst
odoo/addons/animal_medicament/security/ir.model.access.csv
odoo/addons/animal_medicament/static/description/icon.png
odoo/addons/animal_medicament/static/description/index.html
odoo/addons/animal_medicament/views/posology.xml
odoo/addons/animal_medicament/views/product.xml
odoo14_addon_animal_medicament-14.0.1.1.1.dev8.dist-info/METADATA
odoo14_addon_animal_medicament-14.0.1.1.1.dev8.dist-info/WHEEL
odoo14_addon_animal_medicament-14.0.1.1.1.dev8.dist-info/top_level.txt
odoo14_addon_animal_medicament-14.0.1.1.1.dev8.dist-info/RECORD
