Metadata-Version: 2.1
Name: odoo14-addon-animal_medicament
Version: 14.0.1.1.1.dev8
Requires-Python: >=3.6
Requires-Dist: odoo14-addon-animal
Requires-Dist: odoo>=14.0a,<14.1dev
Summary: Drug posologies definition for animals
Home-page: https://github.com/OCA/vertical-agriculture
License: AGPL-3
Author: Akretion, Odoo Community Association (OCA)
Author-email: support@odoo-community.org
Classifier: Programming Language :: Python
Classifier: Framework :: Odoo
Classifier: Framework :: Odoo :: 14.0
Classifier: License :: OSI Approved :: GNU Affero General Public License v3
